{"scissors": "75", "tennis racket": "37", "carriage": "118", "stop sign": "11", "fire hydrant": "10", "giraffe": "23", "horse": "17", "trumpet": "102", "keyboard": "65", "traffic light": "9", "car": "2", "surfboard": "36", "lemon": "112", "umbrella": "25", "barrel/bucket": "130", "chair": "55", "microphone": "122", "cake": "54", "pumpkin": "111", "pizza": "52", "orange": "48", "cow": "19", "piano": "101", "converter": "121", "parking meter": "12", "dining table": "59", "backpack": "24", "tomato": "109", "tie": "27", "zebra": "22", "bed": "58", "pepper": "110", "donut": "53", "vase": "74", "scale": "125", "meat balls": "117", "stool": "126", "sandwich": "47", "suitcase": "28", "cell phone": "66", "oven": "68", "pen/pencil": "124", "bottle": "38", "motorcycle": "3", "snowboard": "31", "wine glass": "39", "sink": "70", "carrot": "50", "stapler": "123", "bench": "13", "boat": "8", "sports ball": "79", "knife": "42", "baseball glove": "34", "remote": "64", "hot dog": "51", "toothbrush": "78", "mouse": "63", "refrigerator": "71", "necklace": "138", "plate": "134", "train": "6", "clutch": "135", "bowl": "44", "bread": "115", "microwave": "67", "toothpaste": "131", "clock": "73", "printer": "120", "elephant": "20", "skis": "30", "gas stove": "127", "life saver": "104", "broccoli": "49", "lantern": "103", "bird": "14", "pear": "114", "toilet": "60", "luggage": "137", "vent": "128", "handbag": "26", "trophy": "139", "laptop": "62", "cup": "40", "person": "0", "pigeon": "108", "bicycle": "1", "hockey": "105", "canned": "116", "sheep": "18", "dog": "16", "tv": "61", "cat": "15", "toaster": "69", "spoon": "43", "airplane": "4", "kite": "32", "couch": "56", "fork": "41", "potted plant": "57", "frisbee": "29", "teddy bear": "76", "cabinet/shelf": "132", "washing machine": "129", "cymbal": "100", "fish": "106", "baseball bat": "33", "strawberry": "113", "hair drier": "77", "skateboard": "35", "bear": "21", "banana": "45", "bus": "5", "hat": "136", "camel": "107", "donkey": "119", "truck": "7", "book": "72", "apple": "46", "air conditioner": "133"}